fermi/__init__.py
fermi/economic_fitness_complexity.py
fermi/matrix_processor.py
fermi/prediction_module.py
fermi/relatedness_metrics.py
fermi/validation_metrics.py
fermi/old_modules/comparative_advantage.py
fermi/old_modules/raw_matrix_processor.py
fermi_cref-0.2.0.dist-info/licenses/LICENSE
fermi_cref-0.2.0.dist-info/METADATA
fermi_cref-0.2.0.dist-info/WHEEL
fermi_cref-0.2.0.dist-info/top_level.txt
fermi_cref-0.2.0.dist-info/RECORD
