Metadata-Version: 2.4
Name: fermi-cref
Version: 0.2.0
Summary: the FitnEss, the Relatedness, and other MetrIcs
Author-email: Lorenzo Buffa <lorenzo.buffa@cref.it>, Daniele Cirulli <daniele.cirulli@cref.it>, Aurelio Patelli <aurelio.patelli@cref.it>, Riccardo Piombo <riccardo.piombo@cref.it>, Filippo Santoro <filippo.santoro@cref.it>, Valeria Secchini <valeria.secchini@cref.it>, Matteo Straccamore <matteo.straccamore@cref.it>
License: MIT
Project-URL: Homepage, https://github.com/EFC-data/fermi
Project-URL: Bug Tracker, https://github.com/EFC-data/fermi/issues
Classifier: License :: OSI Approved :: MIT License
Classifier: Programming Language :: Python :: 3
Classifier: Operating System :: OS Independent
Requires-Python: >=3.9
License-File: LICENSE
Requires-Dist: numpy>=1.24
Requires-Dist: pandas>=1.5
Requires-Dist: matplotlib>=3.5
Requires-Dist: scipy>=1.9
Requires-Dist: networkx>=2.6
Requires-Dist: bokeh>=2.4
Requires-Dist: tqdm>=4.64
Requires-Dist: scikit-learn>=1.2
Requires-Dist: bicm>=3.4.0
Dynamic: license-file
